examples/__init__.py
examples/simple.py
pushetta/__init__.py
pushetta/exceptions.py
pushetta/pushetta.py
pushetta-1.0.15.dist-info/DESCRIPTION.rst
pushetta-1.0.15.dist-info/METADATA
pushetta-1.0.15.dist-info/metadata.json
pushetta-1.0.15.dist-info/RECORD
pushetta-1.0.15.dist-info/top_level.txt
pushetta-1.0.15.dist-info/WHEEL
