Metadata-Version: 2.0
Name: pushetta
Version: 1.0.15
Summary: Client for Pushetta API
Home-page: https://github.com/guglielmino/pushetta-py
Author: Fabrizio Guglielmino
Author-email: guglielmino@gumino.com
License: MIT
Download-URL: https://github.com/guglielmino/pushetta-py/archive/master.zip
Keywords: pushetta push notifications
Platform: UNKNOWN
Classifier: Development Status :: 4 - Beta
Classifier: Intended Audience :: Developers
Classifier: Topic :: Software Development :: Libraries
Classifier: Topic :: System :: Monitoring
Classifier: License :: OSI Approved :: MIT License
Classifier: Programming Language :: Python :: 2.7
Classifier: Programming Language :: Python :: 3
Requires-Dist: future
Requires-Dist: paho-mqtt
